cadetrdm/__init__.py
cadetrdm/conda_env_utils.py
cadetrdm/initialize_repo.py
cadetrdm/repositories.py
cadetrdm/utils.py
tests/__init__.py
tests/test_git_adapter.py
CADETRDM-0.1.1.dist-info/LICENSE
CADETRDM-0.1.1.dist-info/METADATA
CADETRDM-0.1.1.dist-info/WHEEL
CADETRDM-0.1.1.dist-info/entry_points.txt
CADETRDM-0.1.1.dist-info/top_level.txt
CADETRDM-0.1.1.dist-info/RECORD
